project_bootstrap/__init__.py
project_bootstrap/__main__.py
project_bootstrap/templates/node.md
project_bootstrap/templates/python.md
project_bootstrap/templates/swift.md
project_bootstrap-0.0.10.dist-info/METADATA
project_bootstrap-0.0.10.dist-info/WHEEL
project_bootstrap-0.0.10.dist-info/entry_points.txt
project_bootstrap-0.0.10.dist-info/top_level.txt
project_bootstrap-0.0.10.dist-info/RECORD
