Metadata-Version: 2.4
Name: project-bootstrap
Version: 0.0.10
Author-email: roobert <roobert@gmail.com>
License-Expression: MIT
Project-URL: Homepage, https://github.com/roobert/project-bootstrap
Project-URL: Bug Tracker, https://github.com/roobert/project-bootstrap/issues
Classifier: Programming Language :: Python :: 3
Classifier: Operating System :: OS Independent
Requires-Python: >=3.9
Requires-Dist: requests
Requires-Dist: beautifulsoup4
Requires-Dist: urllib3<2
